{"cameraMode":{"drawMode":2,"name":"Shaded Wireframe","section":"Shading Mode"},"sceneLighting":true,"audioPlay":false,"sceneViewState":{"m_AlwaysRefresh":false,"showFog":true,"showSkybox":true,"showFlares":true,"showImageEffects":true,"showParticleSystems":true,"showVisualEffectGraphs":true,"m_FxEnabled":true},"in2DMode":false,"pivot":{"x":1920.0,"y":1080.0,"z":0.0},"rotation":{"x":0.4727460443973541,"y":0.5261238813400269,"z":-0.4756031632423401,"w":0.5229833722114563},"size":2202.9072265625,"orthographic":true}